telegram_cleaner/__init__.py
telegram_cleaner/__main__.py
telegram_cleaner/cleaner.py
telegram_cleaner/cli.py
telegram_cleaner/color_handler.py
telegram_cleaner/utils.py
telegram_cleaner-0.1.5.dist-info/METADATA
telegram_cleaner-0.1.5.dist-info/WHEEL
telegram_cleaner-0.1.5.dist-info/entry_points.txt
telegram_cleaner-0.1.5.dist-info/RECORD
