Metadata-Version: 2.1
Name: telegram-cleaner
Version: 0.1.5
Summary: 
Author: Senior YAML Developer
Author-email: yamldeveloper@proton.me
Requires-Python: >=3.10,<4.0
Classifier: Programming Language :: Python :: 3
Classifier: Programming Language :: Python :: 3.10
Classifier: Programming Language :: Python :: 3.11
Classifier: Programming Language :: Python :: 3.12
Requires-Dist: pyrogram (>=2.0.99,<3.0.0)
Requires-Dist: tgcrypto (>=1.2.5,<2.0.0)
